magickey/__init__.py
magickey/engine.py
magickey/magics.py
magickey/manager.py
magickey/memory.py
magickey/tasks.py
magickey/prompts/__init__.py
magickey/prompts/meta_prompt.txt
magickey/prompts/system_prompt.txt
magickey-0.8.dist-info/LICENSE
magickey-0.8.dist-info/METADATA
magickey-0.8.dist-info/WHEEL
magickey-0.8.dist-info/top_level.txt
magickey-0.8.dist-info/RECORD
