Metadata-Version: 2.1
Name: magickey
Version: 0.8
Summary: This module provides iPython integration and magics that allow exact, inexact and intellegent code execution.
Home-page: https://gitlab.com/mcaledonensis/magickey
Author: Merlinus Caledonensis
Author-email: merlin@roundtable.game
License: Apache 2.0
License-File: LICENSE
Requires-Dist: openai
Requires-Dist: parsimonious
